{"actor":{"name":"Mickey Rourke","imdb_id":"nm0000620"},"movies":[{"title":"1941","year":1979,"rating":5.8},{"title":"Heaven's Gate","year":1980,"rating":6.8},{"title":"Fade to Black","year":1980,"rating":5.9},{"title":"Body Heat","year":1981,"rating":7.4},{"title":"Diner","year":1982,"rating":7.1},{"title":"Rumble Fish","year":1983,"rating":7.2},{"title":"Eureka","year":1983,"rating":6},{"title":"The Pope of Greenwich Village","year":1984,"rating":6.7},{"title":"Year of the Dragon","year":1985,"rating":6.9},{"title":"9½ Weeks","year":1986,"rating":6},{"title":"Angel Heart","year":1987,"rating":7.3},{"title":"Barfly","year":1987,"rating":7.2},{"title":"A Prayer for the Dying","year":1987,"rating":6.3},{"title":"Homeboy","year":1988,"rating":5.9},{"title":"Wild Orchid","year":1989,"rating":4.6},{"title":"Johnny Handsome","year":1989,"rating":6.2},{"title":"Francesco","year":1989,"rating":6.4},{"title":"Desperate Hours","year":1990,"rating":5.4},{"title":"Harley Davidson and the Marlboro Man","year":1991,"rating":6.2},{"title":"White Sands","year":1992,"rating":6},{"title":"F.T.W.","year":1994,"rating":5.3},{"title":"Fall Time","year":1995,"rating":5.5},{"title":"Bullet","year":1996,"rating":6.5},{"title":"Exit in Red","year":1996,"rating":4.3},{"title":"The Rainmaker","year":1997,"rating":7.2},{"title":"Double Team","year":1997,"rating":4.8},{"title":"Another Nine \u0026 a Half Weeks","year":1997,"rating":3},{"title":"Champions Forever: The Latin Legends","year":1997,"rating":6.2},{"title":"The Thin Red Line","year":1998,"rating":7.6},{"title":"Buffalo '66","year":1998,"rating":7.5},{"title":"Thursday","year":1998,"rating":7.2},{"title":"Point Blank","year":1998,"rating":4.3},{"title":"Out in Fifty","year":1999,"rating":3.8},{"title":"Shades","year":1999,"rating":5.4},{"title":"Shergar","year":1999,"rating":5.4},{"title":"Get Carter","year":2000,"rating":5.2},{"title":"Animal Factory","year":2000,"rating":6.6},{"title":"The Pledge","year":2001,"rating":6.8},{"title":"Fotografia","year":2001,"rating":5.5},{"title":"They Crawl","year":2001,"rating":3.5},{"title":"Spun","year":2002,"rating":6.8},{"title":"Once Upon a Time in Mexico","year":2003,"rating":6.4},{"title":"Masked and Anonymous","year":2003,"rating":5.4},{"title":"Man on Fire","year":2004,"rating":7.7},{"title":"Sin City","year":2005,"rating":8},{"title":"Domino","year":2005,"rating":5.9},{"title":"Alex Rider: Operation Stormbreaker","year":2006,"rating":5.1},{"title":"Death Proof","year":2007,"rating":7},{"title":"The Wrestler","year":2008,"rating":7.9},{"title":"The Informers","year":2008,"rating":5},{"title":"Killshot","year":2008,"rating":6},{"title":"42nd Street: River to River","year":2009,"rating":6.6},{"title":"La traversée du désir","year":2009,"rating":6},{"title":"Iron Man 2","year":2010,"rating":7},{"title":"The Expendables","year":2010,"rating":6.5},{"title":"13","year":2010,"rating":6.1},{"title":"Passion Play","year":2010,"rating":4.6},{"title":"Immortals","year":2011,"rating":6},{"title":"The Courier","year":2012,"rating":4.5},{"title":"Black November","year":2012,"rating":5.4},{"title":"Sunset Strip","year":2012,"rating":6.8},{"title":"True Crime: The Movie","year":2012,"rating":7.7},{"title":"Java Heat","year":2013,"rating":5.1},{"title":"Generation Iron","year":2013,"rating":7.1},{"title":"The Good Son: The Life of Ray Boom Boom Mancini","year":2013,"rating":7.8},{"title":"Sin City: A Dame to Kill For","year":2014,"rating":6.5},{"title":"On Any Sunday: The Next Chapter","year":2014,"rating":7.1},{"title":"Hollywood Banker","year":2014,"rating":7.3},{"title":"Ashby","year":2015,"rating":6.4},{"title":"War Pigs","year":2015,"rating":4.2},{"title":"Skin Traffik","year":2015,"rating":4.5},{"title":"Blunt Force Trauma","year":2015,"rating":4.6},{"title":"WEAPONiZED","year":2016,"rating":4.3},{"title":"Nightmare Cinema","year":2018,"rating":5.4},{"title":"Bob Lazar: Area 51 \u0026 Flying Saucers","year":2018,"rating":5.5},{"title":"Tiger","year":2018,"rating":4.7},{"title":"Berlin, I Love You","year":2019,"rating":4.6},{"title":"Night Walk","year":2019,"rating":7.5},{"title":"The Legion","year":2020,"rating":-1},{"title":"Adverse","year":2020,"rating":8.2},{"title":"Take Back","year":2020,"rating":-1},{"title":"Girl","year":2020,"rating":-1},{"title":"Bisping","year":2020,"rating":-1},{"title":"WarHunt","year":-1,"rating":-1},{"title":"Cursed","year":-1,"rating":-1},{"title":"MR-9","year":-1,"rating":-1},{"title":"3 Days Rising","year":-1,"rating":-1},{"title":"Man of God","year":-1,"rating":-1},{"title":"Long Lonesome Highway: The Story of Michael Parks","year":-1,"rating":-1}]}