{"actor":{"name":"Mads Mikkelsen","imdb_id":"nm0586568"},"movies":[{"title":"Pusher","year":1996,"rating":7.4},{"title":"Angel of the Night","year":1998,"rating":3.9},{"title":"Wildside","year":1998,"rating":6.5},{"title":"Bleeder","year":1999,"rating":6.8},{"title":"Flickering Lights","year":2000,"rating":7.7},{"title":"Shake It","year":2001,"rating":6},{"title":"Monas verden","year":2001,"rating":5.1},{"title":"Open Hearts","year":2002,"rating":7.5},{"title":"I Am Dina","year":2002,"rating":6.6},{"title":"Wilbur Wants to Kill Himself","year":2002,"rating":6.8},{"title":"The Green Butchers","year":2003,"rating":7.3},{"title":"Torremolinos 73","year":2003,"rating":6.6},{"title":"King Arthur","year":2004,"rating":6.3},{"title":"Pusher II","year":2004,"rating":7.4},{"title":"Adam's Apples","year":2005,"rating":7.8},{"title":"Casino Royale","year":2006,"rating":8},{"title":"After the Wedding","year":2006,"rating":7.7},{"title":"Exit","year":2006,"rating":5.8},{"title":"Praga","year":2006,"rating":6.7},{"title":"With Your Permission","year":2007,"rating":5.7},{"title":"Flame \u0026 Citron","year":2008,"rating":7.3},{"title":"Valhalla Rising","year":2009,"rating":6.1},{"title":"The Door","year":2009,"rating":6.7},{"title":"Coco Chanel \u0026 Igor Stravinsky","year":2009,"rating":6.4},{"title":"Clash of the Titans","year":2010,"rating":5.8},{"title":"Moomins and the Comet Chase","year":2010,"rating":6.1},{"title":"The Three Musketeers","year":2011,"rating":5.7},{"title":"The Hunt","year":2012,"rating":8.3},{"title":"A Royal Affair","year":2012,"rating":7.5},{"title":"Move On","year":2012,"rating":5.7},{"title":"Charlie Countryman","year":2013,"rating":6.4},{"title":"Age of Uprising: The Legend of Michael Kohlhaas","year":2013,"rating":6.1},{"title":"The Salvation","year":2014,"rating":6.7},{"title":"Men \u0026 Chicken","year":2015,"rating":6.7},{"title":"Rogue One: A Star Wars Story","year":2016,"rating":7.8},{"title":"Doctor Strange","year":2016,"rating":7.5},{"title":"A Bond for Life: How James Bond Changed My Life","year":2016,"rating":7.4},{"title":"Arctic","year":2018,"rating":6.8},{"title":"At Eternity's Gate","year":2018,"rating":6.9},{"title":"Polar","year":2019,"rating":6.3},{"title":"Druk","year":2020,"rating":-1},{"title":"Retfærdighedens ryttere","year":2020,"rating":-1},{"title":"Chaos Walking","year":2021,"rating":-1},{"title":"Untitled Alexander Payne Film","year":-1,"rating":-1}]}