{"actor":{"name":"Arnold Schwarzenegger","imdb_id":"nm0000216"},"movies":[{"title":"Hercules in New York","year":1970,"rating":3.3},{"title":"The Long Goodbye","year":1973,"rating":7.6},{"title":"Stay Hungry","year":1976,"rating":5.6},{"title":"Pumping Iron","year":1977,"rating":7.4},{"title":"This Is America","year":1977,"rating":6.1},{"title":"The Villain","year":1979,"rating":5.4},{"title":"Scavenger Hunt","year":1979,"rating":6},{"title":"The Comeback","year":1980,"rating":6.6},{"title":"Conan the Barbarian","year":1982,"rating":6.9},{"title":"The Man in the Iron Cage","year":1983,"rating":0},{"title":"The Terminator","year":1984,"rating":8},{"title":"Conan the Destroyer","year":1984,"rating":5.9},{"title":"Commando","year":1985,"rating":6.7},{"title":"Red Sonja","year":1985,"rating":5.1},{"title":"Raw Deal","year":1986,"rating":5.6},{"title":"Predator","year":1987,"rating":7.8},{"title":"The Running Man","year":1987,"rating":6.7},{"title":"Twins","year":1988,"rating":6.1},{"title":"Red Heat","year":1988,"rating":6.1},{"title":"Schwarzenegger: Total Rebuild","year":1988,"rating":6.8},{"title":"Total Recall","year":1990,"rating":7.5},{"title":"Kindergarten Cop","year":1990,"rating":6.1},{"title":"Terminator 2: Judgment Day","year":1991,"rating":8.5},{"title":"Encino Man","year":1992,"rating":5.8},{"title":"Feed","year":1992,"rating":5.7},{"title":"Last Action Hero","year":1993,"rating":6.4},{"title":"Dave","year":1993,"rating":6.8},{"title":"Beretta's Island","year":1993,"rating":2.7},{"title":"The Last Party","year":1993,"rating":6.1},{"title":"True Lies","year":1994,"rating":7.2},{"title":"Junior","year":1994,"rating":4.6},{"title":"A Century of Cinema","year":1994,"rating":5.2},{"title":"Eraser","year":1996,"rating":6.1},{"title":"Jingle All the Way","year":1996,"rating":5.6},{"title":"Batman \u0026 Robin","year":1997,"rating":3.7},{"title":"Stand Tall","year":1997,"rating":6.7},{"title":"Junket Whore","year":1998,"rating":4.3},{"title":"End of Days","year":1999,"rating":5.8},{"title":"The 6th Day","year":2000,"rating":5.9},{"title":"Last Party 2000","year":2001,"rating":6.4},{"title":"Collateral Damage","year":2002,"rating":5.5},{"title":"Terminator 3: Rise of the Machines","year":2003,"rating":6.3},{"title":"The Rundown","year":2003,"rating":6.7},{"title":"Around the World in 80 Days","year":2004,"rating":5.9},{"title":"How Arnold Won the West","year":2004,"rating":5.9},{"title":"WMD: Weapon of Mass Destruction","year":2004,"rating":5},{"title":"The Kid \u0026 I","year":2005,"rating":5.3},{"title":"Pursuit of Equality","year":2005,"rating":6.5},{"title":"Al Franken: God Spoke","year":2006,"rating":6.4},{"title":"Darfur Now","year":2007,"rating":6.8},{"title":"Bigger Stronger Faster*","year":2008,"rating":7.6},{"title":"Why We Train","year":2008,"rating":8.1},{"title":"Being W","year":2008,"rating":6.8},{"title":"Cascadorii dragostei","year":2009,"rating":3.8},{"title":"The Expendables","year":2010,"rating":6.5},{"title":"Gerrymandering","year":2010,"rating":7.1},{"title":"Nuclear Tipping Point","year":2010,"rating":7.3},{"title":"Die Stille der Unschuld - Der Künstler Gottfried Helnwein","year":2010,"rating":8.1},{"title":"Revenge of the Electric Car","year":2011,"rating":7.2},{"title":"Tony Curtis: Driven to Stardom","year":2011,"rating":7.4},{"title":"California State of Mind: The Legacy of Pat Brown","year":2011,"rating":8.4},{"title":"The Expendables 2","year":2012,"rating":6.6},{"title":"Addicted to Fame","year":2012,"rating":3.7},{"title":"Railroader","year":2012,"rating":7.9},{"title":"The Last Stand","year":2013,"rating":6.3},{"title":"Escape Plan","year":2013,"rating":6.7},{"title":"Generation Iron","year":2013,"rating":7.1},{"title":"Milius","year":2013,"rating":7.5},{"title":"ASF25 a Documentary","year":2013,"rating":0},{"title":"The Expendables 3","year":2014,"rating":6.1},{"title":"Sabotage","year":2014,"rating":5.7},{"title":"Boardwalk Hempire: The Rise and Fall of the Medical Kush Beach Club","year":2014,"rating":6.6},{"title":"Terminator Genisys","year":2015,"rating":6.4},{"title":"Maggie","year":2015,"rating":5.6},{"title":"Eddie - Strongman","year":2015,"rating":7.5},{"title":"Aftermath","year":2017,"rating":5.7},{"title":"Killing Gunther","year":2017,"rating":4.7},{"title":"Conor McGregor: Notorious","year":2017,"rating":7.2},{"title":"Generation Iron 2","year":2017,"rating":6.1},{"title":"Wonders of the Sea","year":2017,"rating":6.4},{"title":"Guardians of the Earth","year":2017,"rating":6.1},{"title":"The Game Changers","year":2018,"rating":7.9},{"title":"Terminator: Dark Fate","year":2019,"rating":6.3},{"title":"The Iron Mask","year":2019,"rating":4.6},{"title":"Bruno Sammartino","year":2019,"rating":7.4},{"title":"The Beast: When Eddie Met Arnie","year":2020,"rating":-1},{"title":"Stallone: Frank, That Is","year":2020,"rating":-1},{"title":"Kung Fury 2","year":-1,"rating":-1},{"title":"Triplets","year":-1,"rating":-1},{"title":"The Legend of Conan","year":-1,"rating":-1},{"title":"The Original Action Hero","year":-1,"rating":-1},{"title":"It's a Fabulous World","year":-1,"rating":-1}]}